fwiffos/cli/__init__.py
fwiffos/cli/__main__.py
fwiffos/cli/admin.py
fwiffos/cli/shell.py
fwiffos/cli/sudo.py
fwiffos/cli/test-lmdb.py
fwiffos/core/__init__.py
fwiffos/core/__main__.py
fwiffos/core/admin.py
fwiffos/core/core.py
fwiffos/core/identity.py
fwiffos/core/log.py
fwiffos/post/__init__.py
fwiffos/read/__init__.py
fwiffos/read/gsheets.py
fwiffos/read/twitter.py
fwiffos/write/__init__.py
fwiffos-0.0.23.dist-info/LICENSE
fwiffos-0.0.23.dist-info/METADATA
fwiffos-0.0.23.dist-info/WHEEL
fwiffos-0.0.23.dist-info/entry_points.txt
fwiffos-0.0.23.dist-info/top_level.txt
fwiffos-0.0.23.dist-info/RECORD
