Metadata-Version: 2.1
Name: fwiffos
Version: 0.0.23
Summary: FwiffOS
Home-page: https://github.com/SCUPPERfoundation/fwiffo
Author: SCUPPER™ Foundation
Author-email: info@scupper.org
License: MIT
Platform: UNKNOWN
Classifier: Development Status :: 3 - Alpha
Classifier: Environment :: Console
Classifier: Intended Audience :: Developers
Classifier: License :: OSI Approved :: MIT License
Classifier: Operating System :: POSIX
Classifier: Programming Language :: Python
Classifier: Programming Language :: Python :: 3
Classifier: Topic :: Software Development :: Libraries :: Python Modules
Requires-Dist: fire (>=0.3.1)
Requires-Dist: ipython (>=7.17.0)
Requires-Dist: python-ldap (>=3.3.1)
Requires-Dist: email-validator (>=1.1.2)
Requires-Dist: phonenumbers (>=8.12.12)
